streamtape/Account.py
streamtape/ApiResponse.py
streamtape/BaseConfig.py
streamtape/Convertation.py
streamtape/FileManager.py
streamtape/Remote.py
streamtape/Stream.py
streamtape/Upload.py
streamtape/__init__.py
streamtape-1.0.3.dist-info/LICENSE
streamtape-1.0.3.dist-info/METADATA
streamtape-1.0.3.dist-info/WHEEL
streamtape-1.0.3.dist-info/top_level.txt
streamtape-1.0.3.dist-info/RECORD
