Metadata-Version: 2.1
Name: streamtape
Version: 1.0.3
Summary: Unofficial python api wrapper from https://streamtape.come
Home-page: https://github.com/DevCraftClub/StreamTape
Author-email: Maxim Harder <dev@devcraft.club>
Project-URL: Homepage, https://github.com/DevCraftClub/StreamTape
Project-URL: Issues, https://github.com/DevCraftClub/StreamTape/issues
Project-URL: Docs, https://devcraftclub.github.io/StreamTape/
Classifier: Programming Language :: Python :: 3
Classifier: License :: OSI Approved :: MIT License
Classifier: Operating System :: OS Independent
Requires-Python: >=3.8
License-File: LICENSE
